mennort/__init__.py
mennort/mennort.py
mennort-0.1.0.dist-info/METADATA
mennort-0.1.0.dist-info/WHEEL
mennort-0.1.0.dist-info/top_level.txt
mennort-0.1.0.dist-info/RECORD
