Metadata-Version: 2.1
Name: mennort
Version: 0.1.0
Summary: A module for tracking system info and sending it to a webhook.
Author: johan
Requires-Dist: requests
